pypbee/__init__.py
pypbee/_version.py
pypbee/analysis.py
pypbee/avg_sa.py
pypbee/ds.py
pypbee/edp.py
pypbee/gms.py
pypbee/im.py
pypbee/interp_exterp_model.py
pypbee/matplotlib_setup.py
pypbee/mixture.py
pypbee/multivariate_nataf.py
pypbee/nltha.py
pypbee/prelim_analysis.py
pypbee/psdamha.py
pypbee/psdemha.py
pypbee/psha.py
pypbee/sa.py
pypbee/sa_t.py
pypbee/structural_analysis_platform.py
pypbee/structure.py
pypbee/utility.py
pypbee/pygmm_extension/boore_atkinson_2008.py
pypbee-1.2.0.dist-info/licenses/LICENSE.md
pypbee-1.2.0.dist-info/METADATA
pypbee-1.2.0.dist-info/WHEEL
pypbee-1.2.0.dist-info/top_level.txt
pypbee-1.2.0.dist-info/RECORD
