Metadata-Version: 2.4
Name: pypbee
Version: 1.2.0
Summary: Performance-Based Earthquake Engineering toolkit
Author-email: Angshuman Deb <angshuman311@gmail.com>
License-Expression: MIT
Project-URL: Homepage, https://github.com/angshuman311/PyPBEE
Requires-Python: <3.13,>=3.12
License-File: LICENSE.md
Requires-Dist: numpy>=1.26
Requires-Dist: scipy<=1.15.3
Requires-Dist: matplotlib>=3.8.2
Requires-Dist: pygmm>=0.7.1
Requires-Dist: pathos>=0.3.4
Requires-Dist: pydoe3>=1.0.4
Requires-Dist: xlrd>=2.0.1
Requires-Dist: eqsig>=1.2.17
Requires-Dist: openpyxl>=3.1.5
Requires-Dist: python-benedict>=0.35.0
Requires-Dist: PyQt5<5.16,>=5.15
Requires-Dist: openseespy>=3.7
Provides-Extra: numba
Requires-Dist: numba>=0.61; extra == "numba"
Dynamic: license-file
